rechtspraak_citations_extractor/__init__.py
rechtspraak_citations_extractor/citations_extractor.py
rechtspraak_citations_extractor-1.2.0.dist-info/licenses/LICENSE
rechtspraak_citations_extractor-1.2.0.dist-info/METADATA
rechtspraak_citations_extractor-1.2.0.dist-info/WHEEL
rechtspraak_citations_extractor-1.2.0.dist-info/top_level.txt
rechtspraak_citations_extractor-1.2.0.dist-info/RECORD
