Metadata-Version: 2.4
Name: rechtspraak_citations_extractor
Version: 1.2.0
Summary: Library for extracting rechtspraak citations for provided ECLIs
Author-email: LawTech Lab <law-techlab@maastrichtuniversity.nl>
License:                                  Apache License
Project-URL: Bug Tracker, https://github.com/maastrichtlawtech/rechtspraak_citation_extraction/issues
Project-URL: Build Source, https://github.com/maastrichtlawtech/rechtspraak_citation_extraction/
Keywords: rechtspraak,citations,extractor
Requires-Python: >=3.9
License-File: LICENSE
Requires-Dist: certifi
Requires-Dist: charset-normalizer
Requires-Dist: idna
Requires-Dist: lxml
Requires-Dist: numpy
Requires-Dist: pandas
Requires-Dist: python-dateutil
Requires-Dist: pytz
Requires-Dist: requests
Requires-Dist: six
Requires-Dist: tqdm
Requires-Dist: tzdata
Requires-Dist: rdflib
Requires-Dist: urllib3
Requires-Dist: python-dotenv
Dynamic: license-file
